crinex_filter/__init__.py
crinex_filter/crinex_edge.py
crinex_filter-0.1.dist-info/METADATA
crinex_filter-0.1.dist-info/WHEEL
crinex_filter-0.1.dist-info/top_level.txt
crinex_filter-0.1.dist-info/RECORD
