Metadata-Version: 2.1
Name: crinex-filter
Version: 0.1
Summary: for find skin cancer lesions edge
Home-page: https://github.com/crinex/crinex_filter
Author: Crinex
Author-email: crinexk@gmail.com
License: UNKNOWN
Download-URL: https://github.com/crinex/crinex_filter/archive/master.zip
Keywords: Edge Detection, Segmentation
Platform: UNKNOWN
Classifier: Programming Language :: Python :: 3
Classifier: Programming Language :: Python :: 3.2
Classifier: Programming Language :: Python :: 3.3
Classifier: Programming Language :: Python :: 3.4
Classifier: Programming Language :: Python :: 3.5
Classifier: Programming Language :: Python :: 3.6
Classifier: Programming Language :: Python :: 3.7
Requires-Python: >=3
